{
  "classification": "L2B_N20_ATTEMPT2_WAVE2_MISSING360_MANIFEST_READY",
  "completed_cell_files": [
    {
      "base_seeds": [
        0,
        1,
        2,
        3,
        4,
        5,
        6,
        7,
        8,
        9,
        10,
        11,
        12,
        13,
        14,
        15,
        16,
        17,
        18,
        19
      ],
      "cell_id": "grammar_off__c_off__p_off",
      "result_file": "outputs/cluster3/full_pipeline_grammar_mode_cp_factorial_v1/l2b_n20_attempt2/reduction__fp32/grammar_off__c_off__p_off.jsonl",
      "row_count": 20,
      "shard_id": "reduction__fp32"
    },
    {
      "base_seeds": [
        0,
        1,
        2,
        3,
        4,
        5,
        6,
        7,
        8,
        9,
        10,
        11,
        12,
        13,
        14,
        15,
        16,
        17,
        18,
        19
      ],
      "cell_id": "grammar_off__c_on__p_off",
      "result_file": "outputs/cluster3/full_pipeline_grammar_mode_cp_factorial_v1/l2b_n20_attempt2/reduction__fp32/grammar_off__c_on__p_off.jsonl",
      "row_count": 20,
      "shard_id": "reduction__fp32"
    },
    {
      "base_seeds": [
        0,
        1,
        2,
        3,
        4,
        5,
        6,
        7,
        8,
        9,
        10,
        11,
        12,
        13,
        14,
        15,
        16,
        17,
        18,
        19
      ],
      "cell_id": "grammar_off__c_off__p_on",
      "result_file": "outputs/cluster3/full_pipeline_grammar_mode_cp_factorial_v1/l2b_n20_attempt2/reduction__fp32/grammar_off__c_off__p_on.jsonl",
      "row_count": 20,
      "shard_id": "reduction__fp32"
    },
    {
      "base_seeds": [
        0,
        1,
        2,
        3,
        4,
        5,
        6,
        7,
        8,
        9,
        10,
        11,
        12,
        13,
        14,
        15,
        16,
        17,
        18,
        19
      ],
      "cell_id": "grammar_off__c_on__p_on",
      "result_file": "outputs/cluster3/full_pipeline_grammar_mode_cp_factorial_v1/l2b_n20_attempt2/reduction__fp32/grammar_off__c_on__p_on.jsonl",
      "row_count": 20,
      "shard_id": "reduction__fp32"
    },
    {
      "base_seeds": [
        0,
        1,
        2,
        3,
        4,
        5,
        6,
        7,
        8,
        9,
        10,
        11,
        12,
        13,
        14,
        15,
        16,
        17,
        18,
        19
      ],
      "cell_id": "template_upper_bound__c_off__p_off",
      "result_file": "outputs/cluster3/full_pipeline_grammar_mode_cp_factorial_v1/l2b_n20_attempt2/reduction__fp32/template_upper_bound__c_off__p_off.jsonl",
      "row_count": 20,
      "shard_id": "reduction__fp32"
    },
    {
      "base_seeds": [
        0,
        1,
        2,
        3,
        4,
        5,
        6,
        7,
        8,
        9,
        10,
        11,
        12,
        13,
        14,
        15,
        16,
        17,
        18,
        19
      ],
      "cell_id": "template_upper_bound__c_on__p_off",
      "result_file": "outputs/cluster3/full_pipeline_grammar_mode_cp_factorial_v1/l2b_n20_attempt2/reduction__fp32/template_upper_bound__c_on__p_off.jsonl",
      "row_count": 20,
      "shard_id": "reduction__fp32"
    },
    {
      "base_seeds": [
        0,
        1,
        2,
        3,
        4,
        5,
        6,
        7,
        8,
        9,
        10,
        11,
        12,
        13,
        14,
        15,
        16,
        17,
        18,
        19
      ],
      "cell_id": "grammar_off__c_off__p_off",
      "result_file": "outputs/cluster3/full_pipeline_grammar_mode_cp_factorial_v1/l2b_n20_attempt2/reduction__fp16/grammar_off__c_off__p_off.jsonl",
      "row_count": 20,
      "shard_id": "reduction__fp16"
    },
    {
      "base_seeds": [
        0,
        1,
        2,
        3,
        4,
        5,
        6,
        7,
        8,
        9,
        10,
        11,
        12,
        13,
        14,
        15,
        16,
        17,
        18,
        19
      ],
      "cell_id": "grammar_off__c_on__p_off",
      "result_file": "outputs/cluster3/full_pipeline_grammar_mode_cp_factorial_v1/l2b_n20_attempt2/reduction__fp16/grammar_off__c_on__p_off.jsonl",
      "row_count": 20,
      "shard_id": "reduction__fp16"
    },
    {
      "base_seeds": [
        0,
        1,
        2,
        3,
        4,
        5,
        6,
        7,
        8,
        9,
        10,
        11,
        12,
        13,
        14,
        15,
        16,
        17,
        18,
        19
      ],
      "cell_id": "grammar_off__c_off__p_on",
      "result_file": "outputs/cluster3/full_pipeline_grammar_mode_cp_factorial_v1/l2b_n20_attempt2/reduction__fp16/grammar_off__c_off__p_on.jsonl",
      "row_count": 20,
      "shard_id": "reduction__fp16"
    },
    {
      "base_seeds": [
        0,
        1,
        2,
        3,
        4,
        5,
        6,
        7,
        8,
        9,
        10,
        11,
        12,
        13,
        14,
        15,
        16,
        17,
        18,
        19
      ],
      "cell_id": "grammar_off__c_on__p_on",
      "result_file": "outputs/cluster3/full_pipeline_grammar_mode_cp_factorial_v1/l2b_n20_attempt2/reduction__fp16/grammar_off__c_on__p_on.jsonl",
      "row_count": 20,
      "shard_id": "reduction__fp16"
    },
    {
      "base_seeds": [
        0,
        1,
        2,
        3,
        4,
        5,
        6,
        7,
        8,
        9,
        10,
        11,
        12,
        13,
        14,
        15,
        16,
        17,
        18,
        19
      ],
      "cell_id": "template_upper_bound__c_off__p_off",
      "result_file": "outputs/cluster3/full_pipeline_grammar_mode_cp_factorial_v1/l2b_n20_attempt2/reduction__fp16/template_upper_bound__c_off__p_off.jsonl",
      "row_count": 20,
      "shard_id": "reduction__fp16"
    },
    {
      "base_seeds": [
        0,
        1,
        2,
        3,
        4,
        5,
        6,
        7,
        8,
        9,
        10,
        11,
        12,
        13,
        14,
        15,
        16,
        17,
        18,
        19
      ],
      "cell_id": "template_upper_bound__c_on__p_off",
      "result_file": "outputs/cluster3/full_pipeline_grammar_mode_cp_factorial_v1/l2b_n20_attempt2/reduction__fp16/template_upper_bound__c_on__p_off.jsonl",
      "row_count": 20,
      "shard_id": "reduction__fp16"
    },
    {
      "base_seeds": [
        0,
        1,
        2,
        3,
        4,
        5,
        6,
        7,
        8,
        9,
        10,
        11,
        12,
        13,
        14,
        15,
        16,
        17,
        18,
        19
      ],
      "cell_id": "grammar_off__c_off__p_off",
      "result_file": "outputs/cluster3/full_pipeline_grammar_mode_cp_factorial_v1/l2b_n20_attempt2/reduction__bf16/grammar_off__c_off__p_off.jsonl",
      "row_count": 20,
      "shard_id": "reduction__bf16"
    },
    {
      "base_seeds": [
        0,
        1,
        2,
        3,
        4,
        5,
        6,
        7,
        8,
        9,
        10,
        11,
        12,
        13,
        14,
        15,
        16,
        17,
        18,
        19
      ],
      "cell_id": "grammar_off__c_on__p_off",
      "result_file": "outputs/cluster3/full_pipeline_grammar_mode_cp_factorial_v1/l2b_n20_attempt2/reduction__bf16/grammar_off__c_on__p_off.jsonl",
      "row_count": 20,
      "shard_id": "reduction__bf16"
    },
    {
      "base_seeds": [
        0,
        1,
        2,
        3,
        4,
        5,
        6,
        7,
        8,
        9,
        10,
        11,
        12,
        13,
        14,
        15,
        16,
        17,
        18,
        19
      ],
      "cell_id": "grammar_off__c_off__p_on",
      "result_file": "outputs/cluster3/full_pipeline_grammar_mode_cp_factorial_v1/l2b_n20_attempt2/reduction__bf16/grammar_off__c_off__p_on.jsonl",
      "row_count": 20,
      "shard_id": "reduction__bf16"
    },
    {
      "base_seeds": [
        0,
        1,
        2,
        3,
        4,
        5,
        6,
        7,
        8,
        9,
        10,
        11,
        12,
        13,
        14,
        15,
        16,
        17,
        18,
        19
      ],
      "cell_id": "grammar_off__c_on__p_on",
      "result_file": "outputs/cluster3/full_pipeline_grammar_mode_cp_factorial_v1/l2b_n20_attempt2/reduction__bf16/grammar_off__c_on__p_on.jsonl",
      "row_count": 20,
      "shard_id": "reduction__bf16"
    },
    {
      "base_seeds": [
        0,
        1,
        2,
        3,
        4,
        5,
        6,
        7,
        8,
        9,
        10,
        11,
        12,
        13,
        14,
        15,
        16,
        17,
        18,
        19
      ],
      "cell_id": "template_upper_bound__c_off__p_off",
      "result_file": "outputs/cluster3/full_pipeline_grammar_mode_cp_factorial_v1/l2b_n20_attempt2/reduction__bf16/template_upper_bound__c_off__p_off.jsonl",
      "row_count": 20,
      "shard_id": "reduction__bf16"
    },
    {
      "base_seeds": [
        0,
        1,
        2,
        3,
        4,
        5,
        6,
        7,
        8,
        9,
        10,
        11,
        12,
        13,
        14,
        15,
        16,
        17,
        18,
        19
      ],
      "cell_id": "template_upper_bound__c_on__p_off",
      "result_file": "outputs/cluster3/full_pipeline_grammar_mode_cp_factorial_v1/l2b_n20_attempt2/reduction__bf16/template_upper_bound__c_on__p_off.jsonl",
      "row_count": 20,
      "shard_id": "reduction__bf16"
    }
  ],
  "completed_logical_key_count": 360,
  "duplicate_logical_keys": 0,
  "expected_lane_a_rows": 360,
  "lane_a_cell_selector": "template_upper_bound__c_off__p_on,template_upper_bound__c_on__p_on,task_agnostic__c_off__p_off,task_agnostic__c_on__p_off,task_agnostic__c_off__p_on,task_agnostic__c_on__p_on",
  "lane_a_namespace": "l2b_n20_attempt2_wave2_missing360_recovery",
  "lane_a_stage": "l2b_n20_attempt2_wave2_missing360_recovery_full_coverage",
  "manifest_id": "l2b_n20_attempt2_wave2_missing360_recovery_manifest_v1",
  "missing_cell_files": [
    {
      "base_seeds": [
        0,
        1,
        2,
        3,
        4,
        5,
        6,
        7,
        8,
        9,
        10,
        11,
        12,
        13,
        14,
        15,
        16,
        17,
        18,
        19
      ],
      "cell_id": "template_upper_bound__c_off__p_on",
      "result_file": "outputs/cluster3/full_pipeline_grammar_mode_cp_factorial_v1/l2b_n20_attempt2/reduction__fp32/template_upper_bound__c_off__p_on.jsonl",
      "row_count": 20,
      "shard_id": "reduction__fp32"
    },
    {
      "base_seeds": [
        0,
        1,
        2,
        3,
        4,
        5,
        6,
        7,
        8,
        9,
        10,
        11,
        12,
        13,
        14,
        15,
        16,
        17,
        18,
        19
      ],
      "cell_id": "template_upper_bound__c_on__p_on",
      "result_file": "outputs/cluster3/full_pipeline_grammar_mode_cp_factorial_v1/l2b_n20_attempt2/reduction__fp32/template_upper_bound__c_on__p_on.jsonl",
      "row_count": 20,
      "shard_id": "reduction__fp32"
    },
    {
      "base_seeds": [
        0,
        1,
        2,
        3,
        4,
        5,
        6,
        7,
        8,
        9,
        10,
        11,
        12,
        13,
        14,
        15,
        16,
        17,
        18,
        19
      ],
      "cell_id": "task_agnostic__c_off__p_off",
      "result_file": "outputs/cluster3/full_pipeline_grammar_mode_cp_factorial_v1/l2b_n20_attempt2/reduction__fp32/task_agnostic__c_off__p_off.jsonl",
      "row_count": 20,
      "shard_id": "reduction__fp32"
    },
    {
      "base_seeds": [
        0,
        1,
        2,
        3,
        4,
        5,
        6,
        7,
        8,
        9,
        10,
        11,
        12,
        13,
        14,
        15,
        16,
        17,
        18,
        19
      ],
      "cell_id": "task_agnostic__c_on__p_off",
      "result_file": "outputs/cluster3/full_pipeline_grammar_mode_cp_factorial_v1/l2b_n20_attempt2/reduction__fp32/task_agnostic__c_on__p_off.jsonl",
      "row_count": 20,
      "shard_id": "reduction__fp32"
    },
    {
      "base_seeds": [
        0,
        1,
        2,
        3,
        4,
        5,
        6,
        7,
        8,
        9,
        10,
        11,
        12,
        13,
        14,
        15,
        16,
        17,
        18,
        19
      ],
      "cell_id": "task_agnostic__c_off__p_on",
      "result_file": "outputs/cluster3/full_pipeline_grammar_mode_cp_factorial_v1/l2b_n20_attempt2/reduction__fp32/task_agnostic__c_off__p_on.jsonl",
      "row_count": 20,
      "shard_id": "reduction__fp32"
    },
    {
      "base_seeds": [
        0,
        1,
        2,
        3,
        4,
        5,
        6,
        7,
        8,
        9,
        10,
        11,
        12,
        13,
        14,
        15,
        16,
        17,
        18,
        19
      ],
      "cell_id": "task_agnostic__c_on__p_on",
      "result_file": "outputs/cluster3/full_pipeline_grammar_mode_cp_factorial_v1/l2b_n20_attempt2/reduction__fp32/task_agnostic__c_on__p_on.jsonl",
      "row_count": 20,
      "shard_id": "reduction__fp32"
    },
    {
      "base_seeds": [
        0,
        1,
        2,
        3,
        4,
        5,
        6,
        7,
        8,
        9,
        10,
        11,
        12,
        13,
        14,
        15,
        16,
        17,
        18,
        19
      ],
      "cell_id": "template_upper_bound__c_off__p_on",
      "result_file": "outputs/cluster3/full_pipeline_grammar_mode_cp_factorial_v1/l2b_n20_attempt2/reduction__fp16/template_upper_bound__c_off__p_on.jsonl",
      "row_count": 20,
      "shard_id": "reduction__fp16"
    },
    {
      "base_seeds": [
        0,
        1,
        2,
        3,
        4,
        5,
        6,
        7,
        8,
        9,
        10,
        11,
        12,
        13,
        14,
        15,
        16,
        17,
        18,
        19
      ],
      "cell_id": "template_upper_bound__c_on__p_on",
      "result_file": "outputs/cluster3/full_pipeline_grammar_mode_cp_factorial_v1/l2b_n20_attempt2/reduction__fp16/template_upper_bound__c_on__p_on.jsonl",
      "row_count": 20,
      "shard_id": "reduction__fp16"
    },
    {
      "base_seeds": [
        0,
        1,
        2,
        3,
        4,
        5,
        6,
        7,
        8,
        9,
        10,
        11,
        12,
        13,
        14,
        15,
        16,
        17,
        18,
        19
      ],
      "cell_id": "task_agnostic__c_off__p_off",
      "result_file": "outputs/cluster3/full_pipeline_grammar_mode_cp_factorial_v1/l2b_n20_attempt2/reduction__fp16/task_agnostic__c_off__p_off.jsonl",
      "row_count": 20,
      "shard_id": "reduction__fp16"
    },
    {
      "base_seeds": [
        0,
        1,
        2,
        3,
        4,
        5,
        6,
        7,
        8,
        9,
        10,
        11,
        12,
        13,
        14,
        15,
        16,
        17,
        18,
        19
      ],
      "cell_id": "task_agnostic__c_on__p_off",
      "result_file": "outputs/cluster3/full_pipeline_grammar_mode_cp_factorial_v1/l2b_n20_attempt2/reduction__fp16/task_agnostic__c_on__p_off.jsonl",
      "row_count": 20,
      "shard_id": "reduction__fp16"
    },
    {
      "base_seeds": [
        0,
        1,
        2,
        3,
        4,
        5,
        6,
        7,
        8,
        9,
        10,
        11,
        12,
        13,
        14,
        15,
        16,
        17,
        18,
        19
      ],
      "cell_id": "task_agnostic__c_off__p_on",
      "result_file": "outputs/cluster3/full_pipeline_grammar_mode_cp_factorial_v1/l2b_n20_attempt2/reduction__fp16/task_agnostic__c_off__p_on.jsonl",
      "row_count": 20,
      "shard_id": "reduction__fp16"
    },
    {
      "base_seeds": [
        0,
        1,
        2,
        3,
        4,
        5,
        6,
        7,
        8,
        9,
        10,
        11,
        12,
        13,
        14,
        15,
        16,
        17,
        18,
        19
      ],
      "cell_id": "task_agnostic__c_on__p_on",
      "result_file": "outputs/cluster3/full_pipeline_grammar_mode_cp_factorial_v1/l2b_n20_attempt2/reduction__fp16/task_agnostic__c_on__p_on.jsonl",
      "row_count": 20,
      "shard_id": "reduction__fp16"
    },
    {
      "base_seeds": [
        0,
        1,
        2,
        3,
        4,
        5,
        6,
        7,
        8,
        9,
        10,
        11,
        12,
        13,
        14,
        15,
        16,
        17,
        18,
        19
      ],
      "cell_id": "template_upper_bound__c_off__p_on",
      "result_file": "outputs/cluster3/full_pipeline_grammar_mode_cp_factorial_v1/l2b_n20_attempt2/reduction__bf16/template_upper_bound__c_off__p_on.jsonl",
      "row_count": 20,
      "shard_id": "reduction__bf16"
    },
    {
      "base_seeds": [
        0,
        1,
        2,
        3,
        4,
        5,
        6,
        7,
        8,
        9,
        10,
        11,
        12,
        13,
        14,
        15,
        16,
        17,
        18,
        19
      ],
      "cell_id": "template_upper_bound__c_on__p_on",
      "result_file": "outputs/cluster3/full_pipeline_grammar_mode_cp_factorial_v1/l2b_n20_attempt2/reduction__bf16/template_upper_bound__c_on__p_on.jsonl",
      "row_count": 20,
      "shard_id": "reduction__bf16"
    },
    {
      "base_seeds": [
        0,
        1,
        2,
        3,
        4,
        5,
        6,
        7,
        8,
        9,
        10,
        11,
        12,
        13,
        14,
        15,
        16,
        17,
        18,
        19
      ],
      "cell_id": "task_agnostic__c_off__p_off",
      "result_file": "outputs/cluster3/full_pipeline_grammar_mode_cp_factorial_v1/l2b_n20_attempt2/reduction__bf16/task_agnostic__c_off__p_off.jsonl",
      "row_count": 20,
      "shard_id": "reduction__bf16"
    },
    {
      "base_seeds": [
        0,
        1,
        2,
        3,
        4,
        5,
        6,
        7,
        8,
        9,
        10,
        11,
        12,
        13,
        14,
        15,
        16,
        17,
        18,
        19
      ],
      "cell_id": "task_agnostic__c_on__p_off",
      "result_file": "outputs/cluster3/full_pipeline_grammar_mode_cp_factorial_v1/l2b_n20_attempt2/reduction__bf16/task_agnostic__c_on__p_off.jsonl",
      "row_count": 20,
      "shard_id": "reduction__bf16"
    },
    {
      "base_seeds": [
        0,
        1,
        2,
        3,
        4,
        5,
        6,
        7,
        8,
        9,
        10,
        11,
        12,
        13,
        14,
        15,
        16,
        17,
        18,
        19
      ],
      "cell_id": "task_agnostic__c_off__p_on",
      "result_file": "outputs/cluster3/full_pipeline_grammar_mode_cp_factorial_v1/l2b_n20_attempt2/reduction__bf16/task_agnostic__c_off__p_on.jsonl",
      "row_count": 20,
      "shard_id": "reduction__bf16"
    },
    {
      "base_seeds": [
        0,
        1,
        2,
        3,
        4,
        5,
        6,
        7,
        8,
        9,
        10,
        11,
        12,
        13,
        14,
        15,
        16,
        17,
        18,
        19
      ],
      "cell_id": "task_agnostic__c_on__p_on",
      "result_file": "outputs/cluster3/full_pipeline_grammar_mode_cp_factorial_v1/l2b_n20_attempt2/reduction__bf16/task_agnostic__c_on__p_on.jsonl",
      "row_count": 20,
      "shard_id": "reduction__bf16"
    }
  ],
  "missing_logical_key_count": 360,
  "partial_cell_files": [],
  "partial_logical_key_count": 0,
  "read_only_source_artifacts": true,
  "source_namespace": "l2b_n20_attempt2",
  "source_scope": "wave_2 / wave:3:3 / reduction fp32,fp16,bf16",
  "source_stage": "l2b_n20_attempt2_full_coverage"
}
